opsas/__init__.py
opsas/utils/BaseDataType.py
opsas/utils/BasicUtilClass.py
opsas/utils/ConfigClient.py
opsas/utils/HttpSession.py
opsas/utils/SlackLogHandler.py
opsas/utils/__init__.py
opsas_pylib-0.2.2.dist-info/LICENSE
opsas_pylib-0.2.2.dist-info/METADATA
opsas_pylib-0.2.2.dist-info/WHEEL
opsas_pylib-0.2.2.dist-info/top_level.txt
opsas_pylib-0.2.2.dist-info/RECORD
